torchcodec/__init__.py
torchcodec/_frame.py
torchcodec/_internally_replaced_utils.py
torchcodec/libtorchcodec_core4.so
torchcodec/libtorchcodec_core5.so
torchcodec/libtorchcodec_core6.so
torchcodec/libtorchcodec_core7.so
torchcodec/libtorchcodec_core8.so
torchcodec/libtorchcodec_custom_ops4.so
torchcodec/libtorchcodec_custom_ops5.so
torchcodec/libtorchcodec_custom_ops6.so
torchcodec/libtorchcodec_custom_ops7.so
torchcodec/libtorchcodec_custom_ops8.so
torchcodec/libtorchcodec_pybind_ops4.so
torchcodec/libtorchcodec_pybind_ops5.so
torchcodec/libtorchcodec_pybind_ops6.so
torchcodec/libtorchcodec_pybind_ops7.so
torchcodec/libtorchcodec_pybind_ops8.so
torchcodec/version.py
torchcodec/_core/AVIOContextHolder.cpp
torchcodec/_core/AVIOContextHolder.h
torchcodec/_core/AVIOFileLikeContext.cpp
torchcodec/_core/AVIOFileLikeContext.h
torchcodec/_core/AVIOTensorContext.cpp
torchcodec/_core/AVIOTensorContext.h
torchcodec/_core/BetaCudaDeviceInterface.cpp
torchcodec/_core/BetaCudaDeviceInterface.h
torchcodec/_core/CMakeLists.txt
torchcodec/_core/CUDACommon.cpp
torchcodec/_core/CUDACommon.h
torchcodec/_core/Cache.h
torchcodec/_core/CpuDeviceInterface.cpp
torchcodec/_core/CpuDeviceInterface.h
torchcodec/_core/CudaDeviceInterface.cpp
torchcodec/_core/CudaDeviceInterface.h
torchcodec/_core/DeviceInterface.cpp
torchcodec/_core/DeviceInterface.h
torchcodec/_core/Encoder.cpp
torchcodec/_core/Encoder.h
torchcodec/_core/FFMPEGCommon.cpp
torchcodec/_core/FFMPEGCommon.h
torchcodec/_core/FilterGraph.cpp
torchcodec/_core/FilterGraph.h
torchcodec/_core/Frame.cpp
torchcodec/_core/Frame.h
torchcodec/_core/Metadata.h
torchcodec/_core/NVCUVIDRuntimeLoader.cpp
torchcodec/_core/NVCUVIDRuntimeLoader.h
torchcodec/_core/NVDECCache.cpp
torchcodec/_core/NVDECCache.h
torchcodec/_core/SingleStreamDecoder.cpp
torchcodec/_core/SingleStreamDecoder.h
torchcodec/_core/StreamOptions.h
torchcodec/_core/Transform.cpp
torchcodec/_core/Transform.h
paddlecodec-0.1.0.dist-info/METADATA
paddlecodec-0.1.0.dist-info/WHEEL
paddlecodec-0.1.0.dist-info/top_level.txt
paddlecodec-0.1.0.dist-info/RECORD
paddlecodec-0.1.0.dist-info/licenses/LICENSE
